kelvin/api/version.py
kelvin/api/base/__init__.py
kelvin/api/base/api_service_model.py
kelvin/api/base/base_model.py
kelvin/api/base/data_model.py
kelvin/api/base/dataframe_conversion.py
kelvin/api/base/error.py
kelvin/api/base/serialize.py
kelvin/api/base/utils.py
kelvin/api/base/http_client/auth.py
kelvin/api/base/http_client/base_client.py
kelvin/api/base/http_client/env_vars.py
kelvin/api/base/http_client/metadata.py
kelvin/api/base/http_client/retry.py
kelvin/api/base/http_tools/__init__.py
kelvin/api/base/http_tools/history.py
kelvin/api/client/README.md
kelvin/api/client/__init__.py
kelvin/api/client/client.py
kelvin/api/client/error.py
kelvin/api/client/version.py
kelvin/api/client/api/app_parameters.py
kelvin/api/client/api/app_workloads.py
kelvin/api/client/api/apps.py
kelvin/api/client/api/asset.py
kelvin/api/client/api/asset_insights.py
kelvin/api/client/api/control_change.py
kelvin/api/client/api/custom_actions.py
kelvin/api/client/api/data_quality.py
kelvin/api/client/api/data_tag.py
kelvin/api/client/api/datastreams.py
kelvin/api/client/api/deprecated_app_registry.py
kelvin/api/client/api/deprecated_bridge.py
kelvin/api/client/api/deprecated_parameters.py
kelvin/api/client/api/deprecated_workload.py
kelvin/api/client/api/filestorage.py
kelvin/api/client/api/guardrails.py
kelvin/api/client/api/instance.py
kelvin/api/client/api/orchestration.py
kelvin/api/client/api/properties.py
kelvin/api/client/api/recommendation.py
kelvin/api/client/api/secret.py
kelvin/api/client/api/thread.py
kelvin/api/client/api/timeseries.py
kelvin/api/client/api/user.py
kelvin/api/client/api/user_authorization.py
kelvin/api/client/async_api/app_parameters.py
kelvin/api/client/async_api/app_workloads.py
kelvin/api/client/async_api/apps.py
kelvin/api/client/async_api/asset.py
kelvin/api/client/async_api/asset_insights.py
kelvin/api/client/async_api/control_change.py
kelvin/api/client/async_api/custom_actions.py
kelvin/api/client/async_api/data_quality.py
kelvin_python_api_client-1.0.1.dist-info/METADATA
kelvin_python_api_client-1.0.1.dist-info/WHEEL
kelvin_python_api_client-1.0.1.dist-info/top_level.txt
kelvin_python_api_client-1.0.1.dist-info/RECORD
